{
  "generatedAt": "2026-06-04T01:27:00.828Z",
  "sampleSize": 510,
  "confidenceStats": [
    {
      "confidence": 100,
      "totalSignals": 282,
      "completedTrades": 250,
      "wins": 241,
      "losses": 9,
      "open": 32,
      "reliable": true,
      "winRate": 96.4,
      "averageReturn": 2.83,
      "expectancy": 2.73
    },
    {
      "confidence": 66.67,
      "totalSignals": 87,
      "completedTrades": 58,
      "wins": 58,
      "losses": 0,
      "open": 29,
      "reliable": true,
      "winRate": 100,
      "averageReturn": 2.22,
      "expectancy": 2.22
    },
    {
      "confidence": 81,
      "totalSignals": 25,
      "completedTrades": 25,
      "wins": 25,
      "losses": 0,
      "open": 0,
      "reliable": true,
      "winRate": 100,
      "averageReturn": 0.74,
      "expectancy": 0.74
    },
    {
      "confidence": 81.23,
      "totalSignals": 21,
      "completedTrades": 21,
      "wins": 0,
      "losses": 21,
      "open": 0,
      "reliable": true,
      "winRate": 0,
      "averageReturn": -1.29,
      "expectancy": 0
    },
    {
      "confidence": 90,
      "totalSignals": 15,
      "completedTrades": 10,
      "wins": 9,
      "losses": 1,
      "open": 5,
      "reliable": false,
      "winRate": 90,
      "averageReturn": 1.55,
      "expectancy": 1.4
    },
    {
      "confidence": 85.5,
      "totalSignals": 8,
      "completedTrades": 4,
      "wins": 0,
      "losses": 4,
      "open": 4,
      "reliable": false,
      "winRate": 0,
      "averageReturn": -0.65,
      "expectancy": 0
    },
    {
      "confidence": 93.15,
      "totalSignals": 3,
      "completedTrades": 3,
      "wins": 3,
      "losses": 0,
      "open": 0,
      "reliable": false,
      "winRate": 100,
      "averageReturn": 0.74,
      "expectancy": 0.74
    },
    {
      "confidence": 76.67,
      "totalSignals": 3,
      "completedTrades": 3,
      "wins": 3,
      "losses": 0,
      "open": 0,
      "reliable": false,
      "winRate": 100,
      "averageReturn": 3.87,
      "expectancy": 3.87
    },
    {
      "confidence": 64.17,
      "totalSignals": 3,
      "completedTrades": 3,
      "wins": 0,
      "losses": 3,
      "open": 0,
      "reliable": false,
      "winRate": 0,
      "averageReturn": -1.29,
      "expectancy": 0
    },
    {
      "confidence": 60,
      "totalSignals": 11,
      "completedTrades": 3,
      "wins": 1,
      "losses": 2,
      "open": 8,
      "reliable": false,
      "winRate": 33.33,
      "averageReturn": -0.04,
      "expectancy": -0.01
    },
    {
      "confidence": 76.95,
      "totalSignals": 21,
      "completedTrades": 0,
      "wins": 0,
      "losses": 0,
      "open": 21,
      "reliable": false,
      "winRate": 0,
      "averageReturn": 0,
      "expectancy": 0
    },
    {
      "confidence": 73.95,
      "totalSignals": 3,
      "completedTrades": 0,
      "wins": 0,
      "losses": 0,
      "open": 3,
      "reliable": false,
      "winRate": 0,
      "averageReturn": 0,
      "expectancy": 0
    },
    {
      "confidence": 65.41,
      "totalSignals": 3,
      "completedTrades": 0,
      "wins": 0,
      "losses": 0,
      "open": 3,
      "reliable": false,
      "winRate": 0,
      "averageReturn": 0,
      "expectancy": 0
    },
    {
      "confidence": 51,
      "totalSignals": 25,
      "completedTrades": 0,
      "wins": 0,
      "losses": 0,
      "open": 25,
      "reliable": false,
      "winRate": 0,
      "averageReturn": 0,
      "expectancy": 0
    }
  ]
}